bp_help/__init__.py
bp_help/_game.py
bp_help/_print_steps.py
bp_help/controls.py
bp_help/doom_text.py
bp_help/expressions.py
bp_help/print_steps.py
bp_help/steps.py
bp_help/text_gui.py
bp_help-0.2.dist-info/LICENSE
bp_help-0.2.dist-info/METADATA
bp_help-0.2.dist-info/WHEEL
bp_help-0.2.dist-info/entry_points.txt
bp_help-0.2.dist-info/top_level.txt
bp_help-0.2.dist-info/RECORD
