Metadata-Version: 2.1
Name: bp-help
Version: 0.2
Home-page: 
Author: Kasper Munch
Author-email: kasmunch@birc.au.dk
License-File: LICENSE
Requires-Dist: pygments
Requires-Dist: textual
Requires-Dist: rich
Requires-Dist: art
